ecs_compose
