Metadata-Version: 2.1
Name: ecs-compose
Version: 0.9.88
Summary: Amazon ECS cli for docker-compose like deployments
Home-page: https://github.com/fernandosure/ecs-compose
Author: Fernando Sure
Author-email: fernandosure@gmail.com
License: MIT
Download-URL: https://github.com/fernandosure/ecs-compose/archive/0.9.88.tar.gz
Keywords: ECS,AWS
Platform: any
Classifier: Development Status :: 3 - Alpha
Classifier: Environment :: Console
Classifier: Intended Audience :: Developers
Classifier: License :: OSI Approved :: MIT License
Classifier: Operating System :: POSIX
Classifier: Operating System :: MacOS
Classifier: Operating System :: Unix
Classifier: Programming Language :: Python
Classifier: Programming Language :: Python :: 2
Classifier: Programming Language :: Python :: 3
Classifier: Topic :: Software Development :: Libraries :: Python Modules
